toadstool/__init__.py
toadstool/loaders/__init__.py
toadstool/loaders/base_loader.py
toadstool/loaders/config_loader.py
toadstool/loaders/csv_loader.py
toadstool/loaders/gql_loader.py
toadstool/loaders/json_loader.py
toadstool/loaders/toml_loader.py
toadstool/loaders/yaml_loader.py
toadstool/utils/utils.py
toadstool-0.1.0.dist-info/LICENSE
toadstool-0.1.0.dist-info/WHEEL
toadstool-0.1.0.dist-info/METADATA
toadstool-0.1.0.dist-info/RECORD
