Metadata-Version: 2.1
Name: toadstool
Version: 0.1.0
Summary: Python Load Tools Suite
Keywords: import,loader,meta,sys
Author-email: Andrés Alejos <acalejos@proton.me>
Requires-Python: ~=3.10
Classifier: License :: OSI Approved :: MIT License
Classifier: Programming Language :: Python :: 3
Classifier: Topic :: Software Development
Classifier: Topic :: Utilities
Requires-Dist: toadstool[gql] ; extra == "all"
Requires-Dist: toadstool[yaml] ; extra == "all"
Requires-Dist: toadstool[toml] ; extra == "all"
Requires-Dist: graphql_core>=3.2.3 ; extra == "gql"
Requires-Dist: toml >= 0.10.2 ; extra == "toml" and (python_version < "3.11")
Requires-Dist: pyyaml >= 5.3.1 ; extra == "yaml"
Project-URL: Home, https://github.com/acalejos/toadstool
Provides-Extra: all
Provides-Extra: gql
Provides-Extra: toml
Provides-Extra: yaml
